matcher_pcx_synomia/__init__.py
matcher_pcx_synomia/matcher.py
matcher_pcx_synomia-1.1.4.dist-info/LICENSE
matcher_pcx_synomia-1.1.4.dist-info/METADATA
matcher_pcx_synomia-1.1.4.dist-info/WHEEL
matcher_pcx_synomia-1.1.4.dist-info/top_level.txt
matcher_pcx_synomia-1.1.4.dist-info/RECORD
