Metadata-Version: 2.1
Name: matcher-pcx-synomia
Version: 1.1.4
Summary: Extract themes from verbatims
Home-page: UNKNOWN
Author: Synomia
Author-email: pypi@synomia.com
License: UNKNOWN
Platform: UNKNOWN
Classifier: Programming Language :: Python :: 3
